MANIFEST.in
README.md
setup.py
cognitivegeo/__init__.py
cognitivegeo.egg-info/PKG-INFO
cognitivegeo.egg-info/SOURCES.txt
cognitivegeo.egg-info/dependency_links.txt
cognitivegeo.egg-info/requires.txt
cognitivegeo.egg-info/top_level.txt
cognitivegeo/__pycache__/__init__.cpython-36.pyc
cognitivegeo/__pycache__/__init__.cpython-37.pyc
cognitivegeo/demo/demo.proj.npy
cognitivegeo/demo/demo.proj.data/PointSet/pointset1.pts.npy
cognitivegeo/demo/demo.proj.data/PsSeismic/ps_shot_seis.psseis.npy
cognitivegeo/demo/demo.proj.data/Seismic/fault.seis.npy
cognitivegeo/demo/demo.proj.data/Seismic/seis.seis.npy
cognitivegeo/demo/demo.proj.data/Settings/settings.npy
cognitivegeo/demo/demo.proj.data/Survey/survey.srv.npy
cognitivegeo/src/__init__.py
cognitivegeo/src/__pycache__/__init__.cpython-36.pyc
cognitivegeo/src/__pycache__/__init__.cpython-37.pyc
cognitivegeo/src/basic/__init__.py
cognitivegeo/src/basic/curve.py
cognitivegeo/src/basic/data.py
cognitivegeo/src/basic/image.py
cognitivegeo/src/basic/matdict.py
cognitivegeo/src/basic/video.py
cognitivegeo/src/basic/__pycache__/__init__.cpython-36.pyc
cognitivegeo/src/basic/__pycache__/__init__.cpython-37.pyc
cognitivegeo/src/basic/__pycache__/curve.cpython-36.pyc
cognitivegeo/src/basic/__pycache__/curve.cpython-37.pyc
cognitivegeo/src/basic/__pycache__/data.cpython-36.pyc
cognitivegeo/src/basic/__pycache__/data.cpython-37.pyc
cognitivegeo/src/basic/__pycache__/image.cpython-36.pyc
cognitivegeo/src/basic/__pycache__/image.cpython-37.pyc
cognitivegeo/src/basic/__pycache__/matdict.cpython-36.pyc
cognitivegeo/src/basic/__pycache__/matdict.cpython-37.pyc
cognitivegeo/src/basic/__pycache__/video.cpython-36.pyc
cognitivegeo/src/basic/__pycache__/video.cpython-37.pyc
cognitivegeo/src/core/__init__.py
cognitivegeo/src/core/keyboard.py
cognitivegeo/src/core/settings.py
cognitivegeo/src/core/__pycache__/__init__.cpython-36.pyc
cognitivegeo/src/core/__pycache__/__init__.cpython-37.pyc
cognitivegeo/src/core/__pycache__/keyboard.cpython-36.pyc
cognitivegeo/src/core/__pycache__/keyboard.cpython-37.pyc
cognitivegeo/src/core/__pycache__/settings.cpython-36.pyc
cognitivegeo/src/core/__pycache__/settings.cpython-37.pyc
