Metadata-Version: 2.1
Name: cognitivegeo
Version: 1.1.1
Summary: A python tool for geoscience data analysis
Home-page: https://geopyteam.wixsite.com/cognitivegeo
Author: GeoPy Team
Author-email: geopy.info@gmail.com
License: UNKNOWN
Keywords: Geoscience,Seismic
Platform: UNKNOWN
Classifier: Development Status :: 3 - Alpha
Classifier: Intended Audience :: Science/Research
Classifier: Topic :: Scientific/Engineering
Classifier: License :: OSI Approved :: GNU Affero General Public License v3 or later (AGPLv3+)
Classifier: Programming Language :: Python :: 3
Classifier: Operating System :: OS Independent
Requires-Python: >=3.5
